laai/__init__.py
laai/main.py
laai/osds.py
laai/hpo/__init__.py
laai/hpo/client.py
laai/hpo/examples.py
laai/hpo/mlflow_utils.py
laai/hpo/services.py
laai-0.0.5.2.dist-info/METADATA
laai-0.0.5.2.dist-info/WHEEL
laai-0.0.5.2.dist-info/entry_points.txt
laai-0.0.5.2.dist-info/top_level.txt
laai-0.0.5.2.dist-info/RECORD
