Metadata-Version: 2.1
Name: laai
Version: 0.0.5.2
Summary: UNKNOWN
Home-page: UNKNOWN
License: UNKNOWN
Platform: UNKNOWN
Requires-Dist: click
Requires-Dist: python-dotenv
Requires-Dist: docker
Requires-Dist: mlflow
Provides-Extra: optuna
Requires-Dist: optuna ; extra == 'optuna'
Requires-Dist: sklearn ; extra == 'optuna'
Requires-Dist: plotly ; extra == 'optuna'
Requires-Dist: kaleido ; extra == 'optuna'
